mspell/__init__.py
mspell/group_speller.py
mspell/spell_base.py
mspell/speller.py
mspell/spelling_funcs.py
mspell/transpose.py
mspell/unspeller.py
mspell/utils.py
mspell-0.0.4.dist-info/LICENSE
mspell-0.0.4.dist-info/METADATA
mspell-0.0.4.dist-info/WHEEL
mspell-0.0.4.dist-info/top_level.txt
mspell-0.0.4.dist-info/RECORD
