Metadata-Version: 2.1
Name: mspell
Version: 0.0.4
Summary: Spell musical pitches
Home-page: https://github.com/malcolmsailor/mspell
Author: Malcolm Sailor
Author-email: malcolm.sailor@gmail.com
Project-URL: Bug Tracker, https://github.com/malcolmsailor/mspell/issues
Classifier: Programming Language :: Python :: 3
Classifier: License :: OSI Approved :: MIT License
Classifier: Operating System :: OS Independent
License-File: LICENSE
Requires-Dist: numpy
